arboretum/__init__.py
arboretum/core.py
arboretum/libarboretum.so
arboretum_dev-0.1a2.dist-info/METADATA
arboretum_dev-0.1a2.dist-info/WHEEL
arboretum_dev-0.1a2.dist-info/top_level.txt
arboretum_dev-0.1a2.dist-info/RECORD
